kaar/__init__.py
kaar/config.py
kaar/main.py
kaar/utils.py
kaar/pyarmor_runtime_000000/__init__.py
kaar/pyarmor_runtime_000000/pyarmor_runtime.so
kaar/pyarmor_runtime_000000/__pycache__/__init__.cpython-311.pyc
kaar-0.1.1.dist-info/licenses/LICENSE
kaar-0.1.1.dist-info/METADATA
kaar-0.1.1.dist-info/WHEEL
kaar-0.1.1.dist-info/entry_points.txt
kaar-0.1.1.dist-info/top_level.txt
kaar-0.1.1.dist-info/RECORD
