Metadata-Version: 2.4
Name: kaar
Version: 0.1.1
Summary: Kubernetes AI-powered Analysis and Remediation (KAAR) using Amazon Bedrock
Home-page: https://github.com/yourusername/kaar
Author: kashif Rafi
Author-email: rafi.kashif@yahoo.com
License: MIT
License-File: LICENSE
Requires-Dist: boto3>=1.34.0
Requires-Dist: pyyaml>=6.0.1
Dynamic: author
Dynamic: author-email
Dynamic: description
Dynamic: description-content-type
Dynamic: home-page
Dynamic: license
Dynamic: license-file
Dynamic: requires-dist
Dynamic: summary
